pySBB/__init__.py
pySBB/classes.py
pySBB/connection.py
pySBB/query.py
pySBB/sbpy.py
pySBB/utils.py
pySBB-1.0.0.dist-info/LICENSE
pySBB-1.0.0.dist-info/METADATA
pySBB-1.0.0.dist-info/WHEEL
pySBB-1.0.0.dist-info/top_level.txt
pySBB-1.0.0.dist-info/RECORD
