Metadata-Version: 2.1
Name: pySBB
Version: 1.0.0
Summary: An unofficial python wrapper for the SBB api.
Home-page: https://github.com/pasch13/pySBB
Author: Pascal Schärli
Author-email: pas.schaerli@sunrise.ch
License: UNKNOWN
Platform: UNKNOWN
Classifier: Programming Language :: Python :: 3
Classifier: License :: OSI Approved :: MIT License
Classifier: Operating System :: OS Independent
